komodor_mcp/__init__.py
komodor_mcp/api_client.py
komodor_mcp/config.py
komodor_mcp/main.py
komodor_mcp/prompts.py
komodor_mcp/resources.py
komodor_mcp/server.py
komodor_mcp/tools.py
openapi_client/__init__.py
openapi_client/api_client.py
openapi_client/api_response.py
openapi_client/configuration.py
openapi_client/exceptions.py
openapi_client/rest.py
openapi_client/api/__init__.py
openapi_client/api/api_key_api.py
openapi_client/api/audit_logs_api.py
openapi_client/api/clusters_api.py
openapi_client/api/custom_events_api.py
openapi_client/api/events_api.py
openapi_client/api/health_risks_api.py
openapi_client/api/integrations_api.py
openapi_client/api/issues_api.py
openapi_client/api/jobs_api.py
openapi_client/api/klaudia_api.py
openapi_client/api/komodor_cost_api.py
openapi_client/api/kubeconfig_api.py
openapi_client/api/monitors_api.py
openapi_client/api/policies_api.py
openapi_client/api/rbac_api.py
openapi_client/api/real_time_monitors_api.py
openapi_client/api/roles_api.py
openapi_client/api/services_api.py
openapi_client/api/users_api.py
openapi_client/models/__init__.py
openapi_client/models/action.py
openapi_client/models/action_all_of_metadata.py
openapi_client/models/action_result.py
openapi_client/models/action_state.py
openapi_client/models/action_type.py
openapi_client/models/actions_controller_v1_get_all200_response.py
openapi_client/models/api_deprecations_supporting_data.py
openapi_client/models/api_deprecations_supporting_data_deprecated_apis_inner.py
openapi_client/models/api_deprecations_supporting_data_deprecated_apis_inner_resources_inner.py
openapi_client/models/audit_log.py
openapi_client/models/audit_log_category.py
openapi_client/models/audit_log_filters.py
openapi_client/models/audit_log_operation.py
openapi_client/models/audit_log_status.py
openapi_client/models/autoscaler_kind.py
openapi_client/models/basic_violation.py
openapi_client/models/cascading_failure_supporting_data.py
openapi_client/models/certificate_expiration_data.py
komodor_mcp-0.1.3.dist-info/METADATA
komodor_mcp-0.1.3.dist-info/WHEEL
komodor_mcp-0.1.3.dist-info/entry_points.txt
komodor_mcp-0.1.3.dist-info/licenses/LICENSE
komodor_mcp-0.1.3.dist-info/RECORD
