Metadata-Version: 2.4
Name: komodor-mcp
Version: 0.1.3
Summary: Komodor MCP Server - Intelligent AI assistant for Kubernetes infrastructure
Author-email: Komodor <support@komodor.com>
License: Apache-2.0
License-File: LICENSE
Classifier: Development Status :: 3 - Alpha
Classifier: Intended Audience :: Developers
Classifier: License :: OSI Approved :: Apache Software License
Classifier: Programming Language :: Python :: 3
Classifier: Programming Language :: Python :: 3.11
Classifier: Programming Language :: Python :: 3.12
Requires-Python: >=3.11
Requires-Dist: aiohttp-retry>=2.9.1
Requires-Dist: aiohttp>=3.13.2
Requires-Dist: anyio>=4.11.0
Requires-Dist: httpx>=0.28.1
Requires-Dist: lazy-imports>=1.1.0
Requires-Dist: mcp>=1.20.0
Requires-Dist: pydantic-settings>=2.11.0
Requires-Dist: pydantic>=2.12.3
Requires-Dist: python-dateutil>=2.9.0
Requires-Dist: python-dotenv>=1.2.1
Requires-Dist: starlette>=0.50.0
Requires-Dist: structlog>=25.5.0
Requires-Dist: typing-extensions>=4.15.0
Requires-Dist: urllib3>=2.5.0
Requires-Dist: uvicorn>=0.38.0
Provides-Extra: dev
Requires-Dist: black>=25.9.0; extra == 'dev'
Requires-Dist: debugpy>=1.8.17; extra == 'dev'
Requires-Dist: mypy>=1.18.2; extra == 'dev'
Requires-Dist: pytest-asyncio>=1.2.0; extra == 'dev'
Requires-Dist: pytest-httpx>=0.35.0; extra == 'dev'
Requires-Dist: pytest>=8.4.2; extra == 'dev'
Requires-Dist: ruff>=0.14.3; extra == 'dev'
